{
  "views": [
    {
      "content_description": null, 
      "resource_id": null, 
      "text": null, 
      "visible": true, 
      "checkable": false, 
      "children": [
        1, 
        43, 
        44
      ], 
      "size": "1440*2560", 
      "checked": false, 
      "temp_id": 0, 
      "selected": false, 
      "child_count": 3, 
      "content_free_signature": "[class]android.widget.FrameLayout[resource_id]None", 
      "is_password": false, 
      "parent": -1, 
      "focusable": false, 
      "editable": false, 
      "focused": false, 
      "clickable": false, 
      "class": "android.widget.FrameLayout", 
      "scrollable": false, 
      "package": "com.yelp.android", 
      "long_clickable": false, 
      "view_str": "50ebfec6fed5241ded7fa5fc88300f30", 
      "enabled": true, 
      "bounds": [
        [
          0, 
          0
        ], 
        [
          1440, 
          2560
        ]
      ], 
      "signature": "[class]android.widget.FrameLayout[resource_id]None[text]None[enabled,,]"
    }, 
    {
      "content_description": null, 
      "resource_id": null, 
      "text": null, 
      "visible": true, 
      "checkable": false, 
      "children": [
        2
      ], 
      "size": "1440*2392", 
      "checked": false, 
      "temp_id": 1, 
      "selected": false, 
      "child_count": 1, 
      "content_free_signature": "[class]android.widget.LinearLayout[resource_id]None", 
      "is_password": false, 
      "parent": 0, 
      "focusable": false, 
      "editable": false, 
      "focused": false, 
      "clickable": false, 
      "class": "android.widget.LinearLayout", 
      "scrollable": false, 
      "package": "com.yelp.android", 
      "long_clickable": false, 
      "view_str": "f1cb39e3b6a40f82e3178637be8a3166", 
      "enabled": true, 
      "bounds": [
        [
          0, 
          0
        ], 
        [
          1440, 
          2392
        ]
      ], 
      "signature": "[class]android.widget.LinearLayout[resource_id]None[text]None[enabled,,]"
    }, 
    {
      "content_description": null, 
      "resource_id": null, 
      "text": null, 
      "visible": true, 
      "checkable": false, 
      "children": [
        3
      ], 
      "size": "1440*2308", 
      "checked": false, 
      "temp_id": 2, 
      "selected": false, 
      "child_count": 1, 
      "content_free_signature": "[class]android.widget.FrameLayout[resource_id]None", 
      "is_password": false, 
      "parent": 1, 
      "focusable": false, 
      "editable": false, 
      "focused": false, 
      "clickable": false, 
      "class": "android.widget.FrameLayout", 
      "scrollable": false, 
      "package": "com.yelp.android", 
      "long_clickable": false, 
      "view_str": "26aa3b948785501304f35bd30f2842cb", 
      "enabled": true, 
      "bounds": [
        [
          0, 
          84
        ], 
        [
          1440, 
          2392
        ]
      ], 
      "signature": "[class]android.widget.FrameLayout[resource_id]None[text]None[enabled,,]"
    }, 
    {
      "content_description": null, 
      "resource_id": "com.yelp.android:id/action_bar_root", 
      "text": null, 
      "visible": true, 
      "checkable": false, 
      "children": [
        4
      ], 
      "size": "1440*2308", 
      "checked": false, 
      "temp_id": 3, 
      "selected": false, 
      "child_count": 1, 
      "content_free_signature": "[class]android.widget.LinearLayout[resource_id]com.yelp.android:id/action_bar_root", 
      "is_password": false, 
      "parent": 2, 
      "focusable": false, 
      "editable": false, 
      "focused": false, 
      "clickable": false, 
      "class": "android.widget.LinearLayout", 
      "scrollable": false, 
      "package": "com.yelp.android", 
      "long_clickable": false, 
      "view_str": "5de6e4e62a2b5552e142628ed5386cfc", 
      "enabled": true, 
      "bounds": [
        [
          0, 
          84
        ], 
        [
          1440, 
          2392
        ]
      ], 
      "signature": "[class]android.widget.LinearLayout[resource_id]com.yelp.android:id/action_bar_root[text]None[enabled,,]"
    }, 
    {
      "content_description": null, 
      "resource_id": "android:id/content", 
      "text": null, 
      "visible": true, 
      "checkable": false, 
      "children": [
        5
      ], 
      "size": "1440*2308", 
      "checked": false, 
      "temp_id": 4, 
      "selected": false, 
      "child_count": 1, 
      "content_free_signature": "[class]android.widget.FrameLayout[resource_id]android:id/content", 
      "is_password": false, 
      "parent": 3, 
      "focusable": false, 
      "editable": false, 
      "focused": false, 
      "clickable": false, 
      "class": "android.widget.FrameLayout", 
      "scrollable": false, 
      "package": "com.yelp.android", 
      "long_clickable": false, 
      "view_str": "51bbd0838f0d689a744d89fd2532e35a", 
      "enabled": true, 
      "bounds": [
        [
          0, 
          84
        ], 
        [
          1440, 
          2392
        ]
      ], 
      "signature": "[class]android.widget.FrameLayout[resource_id]android:id/content[text]None[enabled,,]"
    }, 
    {
      "content_description": null, 
      "resource_id": "com.yelp.android:id/bottomsheet", 
      "text": null, 
      "visible": true, 
      "checkable": false, 
      "children": [
        6
      ], 
      "size": "1440*2308", 
      "checked": false, 
      "temp_id": 5, 
      "selected": false, 
      "child_count": 1, 
      "content_free_signature": "[class]android.widget.FrameLayout[resource_id]com.yelp.android:id/bottomsheet", 
      "is_password": false, 
      "parent": 4, 
      "focusable": true, 
      "editable": false, 
      "focused": false, 
      "clickable": false, 
      "class": "android.widget.FrameLayout", 
      "scrollable": false, 
      "package": "com.yelp.android", 
      "long_clickable": false, 
      "view_str": "da749dc107abac53f9c7f3b3416f9e54", 
      "enabled": true, 
      "bounds": [
        [
          0, 
          84
        ], 
        [
          1440, 
          2392
        ]
      ], 
      "signature": "[class]android.widget.FrameLayout[resource_id]com.yelp.android:id/bottomsheet[text]None[enabled,,]"
    }, 
    {
      "content_description": null, 
      "resource_id": null, 
      "text": null, 
      "visible": true, 
      "checkable": false, 
      "children": [
        7
      ], 
      "size": "1440*2308", 
      "checked": false, 
      "temp_id": 6, 
      "selected": false, 
      "child_count": 1, 
      "content_free_signature": "[class]android.widget.LinearLayout[resource_id]None", 
      "is_password": false, 
      "parent": 5, 
      "focusable": false, 
      "editable": false, 
      "focused": false, 
      "clickable": false, 
      "class": "android.widget.LinearLayout", 
      "scrollable": false, 
      "package": "com.yelp.android", 
      "long_clickable": false, 
      "view_str": "a839dd752d2e83aa21fc0a5bd59358e5", 
      "enabled": true, 
      "bounds": [
        [
          0, 
          84
        ], 
        [
          1440, 
          2392
        ]
      ], 
      "signature": "[class]android.widget.LinearLayout[resource_id]None[text]None[enabled,,]"
    }, 
    {
      "content_description": null, 
      "resource_id": "com.yelp.android:id/content_frame", 
      "text": null, 
      "visible": true, 
      "checkable": false, 
      "children": [
        8
      ], 
      "size": "1440*2308", 
      "checked": false, 
      "temp_id": 7, 
      "selected": false, 
      "child_count": 1, 
      "content_free_signature": "[class]android.widget.FrameLayout[resource_id]com.yelp.android:id/content_frame", 
      "is_password": false, 
      "parent": 6, 
      "focusable": false, 
      "editable": false, 
      "focused": false, 
      "clickable": false, 
      "class": "android.widget.FrameLayout", 
      "scrollable": false, 
      "package": "com.yelp.android", 
      "long_clickable": false, 
      "view_str": "421d842862e9adca5be9283ff8f8eaea", 
      "enabled": true, 
      "bounds": [
        [
          0, 
          84
        ], 
        [
          1440, 
          2392
        ]
      ], 
      "signature": "[class]android.widget.FrameLayout[resource_id]com.yelp.android:id/content_frame[text]None[enabled,,]"
    }, 
    {
      "content_description": null, 
      "resource_id": "com.yelp.android:id/search_overlay_root", 
      "text": null, 
      "visible": true, 
      "checkable": false, 
      "children": [
        9, 
        16, 
        42
      ], 
      "size": "1440*2308", 
      "checked": false, 
      "temp_id": 8, 
      "selected": false, 
      "child_count": 3, 
      "content_free_signature": "[class]android.widget.RelativeLayout[resource_id]com.yelp.android:id/search_overlay_root", 
      "is_password": false, 
      "parent": 7, 
      "focusable": false, 
      "editable": false, 
      "focused": false, 
      "clickable": false, 
      "class": "android.widget.RelativeLayout", 
      "scrollable": false, 
      "package": "com.yelp.android", 
      "long_clickable": false, 
      "view_str": "37ae420ad1f71857b86dfe8b0eed9fd2", 
      "enabled": true, 
      "bounds": [
        [
          0, 
          84
        ], 
        [
          1440, 
          2392
        ]
      ], 
      "signature": "[class]android.widget.RelativeLayout[resource_id]com.yelp.android:id/search_overlay_root[text]None[enabled,,]"
    }, 
    {
      "content_description": null, 
      "resource_id": "com.yelp.android:id/main_searchboxes", 
      "text": null, 
      "visible": true, 
      "checkable": false, 
      "children": [
        10, 
        14, 
        15
      ], 
      "size": "1440*396", 
      "checked": false, 
      "temp_id": 9, 
      "selected": false, 
      "child_count": 3, 
      "content_free_signature": "[class]android.widget.RelativeLayout[resource_id]com.yelp.android:id/main_searchboxes", 
      "is_password": false, 
      "parent": 8, 
      "focusable": false, 
      "editable": false, 
      "focused": false, 
      "clickable": false, 
      "class": "android.widget.RelativeLayout", 
      "scrollable": false, 
      "package": "com.yelp.android", 
      "long_clickable": false, 
      "view_str": "cca74cc5e929d8601f21a39b95cde49f", 
      "enabled": true, 
      "bounds": [
        [
          0, 
          84
        ], 
        [
          1440, 
          480
        ]
      ], 
      "signature": "[class]android.widget.RelativeLayout[resource_id]com.yelp.android:id/main_searchboxes[text]None[enabled,,]"
    }, 
    {
      "content_description": null, 
      "resource_id": "com.yelp.android:id/search_controls_wrapper", 
      "text": null, 
      "visible": true, 
      "checkable": false, 
      "children": [
        11, 
        12, 
        13
      ], 
      "size": "1230*396", 
      "checked": false, 
      "temp_id": 10, 
      "selected": false, 
      "child_count": 3, 
      "content_free_signature": "[class]android.widget.RelativeLayout[resource_id]com.yelp.android:id/search_controls_wrapper", 
      "is_password": false, 
      "parent": 9, 
      "focusable": false, 
      "editable": false, 
      "focused": false, 
      "clickable": false, 
      "class": "android.widget.RelativeLayout", 
      "scrollable": false, 
      "package": "com.yelp.android", 
      "long_clickable": false, 
      "view_str": "575d052d7c5e7469a0241d26858b4ac2", 
      "enabled": true, 
      "bounds": [
        [
          0, 
          84
        ], 
        [
          1230, 
          480
        ]
      ], 
      "signature": "[class]android.widget.RelativeLayout[resource_id]com.yelp.android:id/search_controls_wrapper[text]None[enabled,,]"
    }, 
    {
      "content_description": null, 
      "resource_id": "com.yelp.android:id/searchbar", 
      "text": "Hair Salons", 
      "visible": true, 
      "checkable": false, 
      "children": [], 
      "size": "1230*196", 
      "checked": false, 
      "temp_id": 11, 
      "selected": false, 
      "child_count": 0, 
      "content_free_signature": "[class]android.widget.EditText[resource_id]com.yelp.android:id/searchbar", 
      "is_password": false, 
      "parent": 10, 
      "focusable": true, 
      "editable": true, 
      "focused": true, 
      "clickable": true, 
      "class": "android.widget.EditText", 
      "scrollable": false, 
      "package": "com.yelp.android", 
      "long_clickable": true, 
      "view_str": "93b008531f68c1e6f9592480122685ce", 
      "enabled": true, 
      "bounds": [
        [
          0, 
          84
        ], 
        [
          1230, 
          280
        ]
      ], 
      "signature": "[class]android.widget.EditText[resource_id]com.yelp.android:id/searchbar[text]Hair Salons[enabled,,]"
    }, 
    {
      "content_description": null, 
      "resource_id": "com.yelp.android:id/separator", 
      "text": null, 
      "visible": true, 
      "checkable": false, 
      "children": [], 
      "size": "1202*4", 
      "checked": false, 
      "temp_id": 12, 
      "selected": false, 
      "child_count": 0, 
      "content_free_signature": "[class]android.view.View[resource_id]com.yelp.android:id/separator", 
      "is_password": false, 
      "parent": 10, 
      "focusable": false, 
      "editable": false, 
      "focused": false, 
      "clickable": false, 
      "class": "android.view.View", 
      "scrollable": false, 
      "package": "com.yelp.android", 
      "long_clickable": false, 
      "view_str": "33dc5c85780fb18e54f8158301f3fd10", 
      "enabled": true, 
      "bounds": [
        [
          28, 
          280
        ], 
        [
          1230, 
          284
        ]
      ], 
      "signature": "[class]android.view.View[resource_id]com.yelp.android:id/separator[text]None[enabled,,]"
    }, 
    {
      "content_description": null, 
      "resource_id": "com.yelp.android:id/locationbar", 
      "text": "Current Location", 
      "visible": true, 
      "checkable": false, 
      "children": [], 
      "size": "1230*196", 
      "checked": false, 
      "temp_id": 13, 
      "selected": false, 
      "child_count": 0, 
      "content_free_signature": "[class]android.widget.EditText[resource_id]com.yelp.android:id/locationbar", 
      "is_password": false, 
      "parent": 10, 
      "focusable": true, 
      "editable": true, 
      "focused": false, 
      "clickable": true, 
      "class": "android.widget.EditText", 
      "scrollable": false, 
      "package": "com.yelp.android", 
      "long_clickable": true, 
      "view_str": "7bbbea9d5ad6bc0f7c0815949ed39fc2", 
      "enabled": true, 
      "bounds": [
        [
          0, 
          284
        ], 
        [
          1230, 
          480
        ]
      ], 
      "signature": "[class]android.widget.EditText[resource_id]com.yelp.android:id/locationbar[text]Current Location[enabled,,]"
    }, 
    {
      "content_description": null, 
      "resource_id": null, 
      "text": null, 
      "visible": true, 
      "checkable": false, 
      "children": [], 
      "size": "4*396", 
      "checked": false, 
      "temp_id": 14, 
      "selected": false, 
      "child_count": 0, 
      "content_free_signature": "[class]android.view.View[resource_id]None", 
      "is_password": false, 
      "parent": 9, 
      "focusable": false, 
      "editable": false, 
      "focused": false, 
      "clickable": false, 
      "class": "android.view.View", 
      "scrollable": false, 
      "package": "com.yelp.android", 
      "long_clickable": false, 
      "view_str": "e9db0b1c8344c054de511148a2179823", 
      "enabled": true, 
      "bounds": [
        [
          1230, 
          84
        ], 
        [
          1234, 
          480
        ]
      ], 
      "signature": "[class]android.view.View[resource_id]None[text]None[enabled,,]"
    }, 
    {
      "content_description": "Search Yelp", 
      "resource_id": "com.yelp.android:id/search_button", 
      "text": null, 
      "visible": true, 
      "checkable": false, 
      "children": [], 
      "size": "126*126", 
      "checked": false, 
      "temp_id": 15, 
      "selected": false, 
      "child_count": 0, 
      "content_free_signature": "[class]android.widget.ImageButton[resource_id]com.yelp.android:id/search_button", 
      "is_password": false, 
      "parent": 9, 
      "focusable": true, 
      "editable": false, 
      "focused": false, 
      "clickable": true, 
      "class": "android.widget.ImageButton", 
      "scrollable": false, 
      "package": "com.yelp.android", 
      "long_clickable": false, 
      "view_str": "c93bc6c3759d5a7bb70769c7059b3ed7", 
      "enabled": true, 
      "bounds": [
        [
          1272, 
          219
        ], 
        [
          1398, 
          345
        ]
      ], 
      "signature": "[class]android.widget.ImageButton[resource_id]com.yelp.android:id/search_button[text]None[enabled,,]"
    }, 
    {
      "content_description": null, 
      "resource_id": "com.yelp.android:id/search_suggest_layout", 
      "text": null, 
      "visible": true, 
      "checkable": false, 
      "children": [
        17
      ], 
      "size": "1440*1146", 
      "checked": false, 
      "temp_id": 16, 
      "selected": false, 
      "child_count": 1, 
      "content_free_signature": "[class]android.widget.FrameLayout[resource_id]com.yelp.android:id/search_suggest_layout", 
      "is_password": false, 
      "parent": 8, 
      "focusable": false, 
      "editable": false, 
      "focused": false, 
      "clickable": false, 
      "class": "android.widget.FrameLayout", 
      "scrollable": false, 
      "package": "com.yelp.android", 
      "long_clickable": false, 
      "view_str": "f60d635acd2382fc8253bee5fe78dddf", 
      "enabled": true, 
      "bounds": [
        [
          0, 
          480
        ], 
        [
          1440, 
          1626
        ]
      ], 
      "signature": "[class]android.widget.FrameLayout[resource_id]com.yelp.android:id/search_suggest_layout[text]None[enabled,,]"
    }, 
    {
      "content_description": null, 
      "resource_id": "com.yelp.android:id/search_suggest", 
      "text": null, 
      "visible": true, 
      "checkable": false, 
      "children": [
        18, 
        22, 
        26, 
        30, 
        34, 
        38
      ], 
      "size": "1440*1146", 
      "checked": false, 
      "temp_id": 17, 
      "selected": false, 
      "child_count": 6, 
      "content_free_signature": "[class]android.widget.ListView[resource_id]com.yelp.android:id/search_suggest", 
      "is_password": false, 
      "parent": 16, 
      "focusable": true, 
      "editable": false, 
      "focused": false, 
      "clickable": true, 
      "class": "android.widget.ListView", 
      "scrollable": false, 
      "package": "com.yelp.android", 
      "long_clickable": false, 
      "view_str": "c909b1ad88089cd6a19477354059bdc3", 
      "enabled": true, 
      "bounds": [
        [
          0, 
          480
        ], 
        [
          1440, 
          1626
        ]
      ], 
      "signature": "[class]android.widget.ListView[resource_id]com.yelp.android:id/search_suggest[text]None[enabled,,]"
    }, 
    {
      "content_description": null, 
      "resource_id": null, 
      "text": null, 
      "visible": true, 
      "checkable": false, 
      "children": [
        19
      ], 
      "size": "1440*191", 
      "checked": false, 
      "temp_id": 18, 
      "selected": false, 
      "child_count": 1, 
      "content_free_signature": "[class]android.widget.RelativeLayout[resource_id]None", 
      "is_password": false, 
      "parent": 17, 
      "focusable": false, 
      "editable": false, 
      "focused": false, 
      "clickable": true, 
      "class": "android.widget.RelativeLayout", 
      "scrollable": false, 
      "package": "com.yelp.android", 
      "long_clickable": false, 
      "view_str": "347f4e721d4ad4625577fb41f924bbec", 
      "enabled": true, 
      "bounds": [
        [
          0, 
          480
        ], 
        [
          1440, 
          671
        ]
      ], 
      "signature": "[class]android.widget.RelativeLayout[resource_id]None[text]None[enabled,,]"
    }, 
    {
      "content_description": null, 
      "resource_id": "com.yelp.android:id/term_description", 
      "text": null, 
      "visible": true, 
      "checkable": false, 
      "children": [
        20, 
        21
      ], 
      "size": "1348*121", 
      "checked": false, 
      "temp_id": 19, 
      "selected": false, 
      "child_count": 2, 
      "content_free_signature": "[class]android.widget.RelativeLayout[resource_id]com.yelp.android:id/term_description", 
      "is_password": false, 
      "parent": 18, 
      "focusable": false, 
      "editable": false, 
      "focused": false, 
      "clickable": false, 
      "class": "android.widget.RelativeLayout", 
      "scrollable": false, 
      "package": "com.yelp.android", 
      "long_clickable": false, 
      "view_str": "27f5af69c25a1d552d94a9ef97fcce2b", 
      "enabled": true, 
      "bounds": [
        [
          46, 
          515
        ], 
        [
          1394, 
          636
        ]
      ], 
      "signature": "[class]android.widget.RelativeLayout[resource_id]com.yelp.android:id/term_description[text]None[enabled,,]"
    }, 
    {
      "content_description": null, 
      "resource_id": "com.yelp.android:id/term", 
      "text": "Hair Salons", 
      "visible": true, 
      "checkable": false, 
      "children": [], 
      "size": "320*85", 
      "checked": false, 
      "temp_id": 20, 
      "selected": false, 
      "child_count": 0, 
      "content_free_signature": "[class]android.widget.TextView[resource_id]com.yelp.android:id/term", 
      "is_password": false, 
      "parent": 19, 
      "focusable": false, 
      "editable": false, 
      "focused": false, 
      "clickable": false, 
      "class": "android.widget.TextView", 
      "scrollable": false, 
      "package": "com.yelp.android", 
      "long_clickable": false, 
      "view_str": "ae2e7a89bcb1621281553d9b6a2f8da6", 
      "enabled": true, 
      "bounds": [
        [
          46, 
          533
        ], 
        [
          366, 
          618
        ]
      ], 
      "signature": "[class]android.widget.TextView[resource_id]com.yelp.android:id/term[text]Hair Salons[enabled,,]"
    }, 
    {
      "content_description": null, 
      "resource_id": "com.yelp.android:id/description", 
      "text": null, 
      "visible": true, 
      "checkable": false, 
      "children": [], 
      "size": "36*121", 
      "checked": false, 
      "temp_id": 21, 
      "selected": false, 
      "child_count": 0, 
      "content_free_signature": "[class]android.widget.TextView[resource_id]com.yelp.android:id/description", 
      "is_password": false, 
      "parent": 19, 
      "focusable": false, 
      "editable": false, 
      "focused": false, 
      "clickable": false, 
      "class": "android.widget.TextView", 
      "scrollable": false, 
      "package": "com.yelp.android", 
      "long_clickable": false, 
      "view_str": "a087ed2f85a36ca33676fb902785bc33", 
      "enabled": true, 
      "bounds": [
        [
          366, 
          515
        ], 
        [
          402, 
          636
        ]
      ], 
      "signature": "[class]android.widget.TextView[resource_id]com.yelp.android:id/description[text]None[enabled,,]"
    }, 
    {
      "content_description": null, 
      "resource_id": null, 
      "text": null, 
      "visible": true, 
      "checkable": false, 
      "children": [
        23
      ], 
      "size": "1440*191", 
      "checked": false, 
      "temp_id": 22, 
      "selected": false, 
      "child_count": 1, 
      "content_free_signature": "[class]android.widget.RelativeLayout[resource_id]None", 
      "is_password": false, 
      "parent": 17, 
      "focusable": false, 
      "editable": false, 
      "focused": false, 
      "clickable": true, 
      "class": "android.widget.RelativeLayout", 
      "scrollable": false, 
      "package": "com.yelp.android", 
      "long_clickable": false, 
      "view_str": "347f4e721d4ad4625577fb41f924bbec", 
      "enabled": true, 
      "bounds": [
        [
          0, 
          671
        ], 
        [
          1440, 
          862
        ]
      ], 
      "signature": "[class]android.widget.RelativeLayout[resource_id]None[text]None[enabled,,]"
    }, 
    {
      "content_description": null, 
      "resource_id": "com.yelp.android:id/term_description", 
      "text": null, 
      "visible": true, 
      "checkable": false, 
      "children": [
        24, 
        25
      ], 
      "size": "1348*121", 
      "checked": false, 
      "temp_id": 23, 
      "selected": false, 
      "child_count": 2, 
      "content_free_signature": "[class]android.widget.RelativeLayout[resource_id]com.yelp.android:id/term_description", 
      "is_password": false, 
      "parent": 22, 
      "focusable": false, 
      "editable": false, 
      "focused": false, 
      "clickable": false, 
      "class": "android.widget.RelativeLayout", 
      "scrollable": false, 
      "package": "com.yelp.android", 
      "long_clickable": false, 
      "view_str": "665ce10a9600e1df491bdc80707c1ca1", 
      "enabled": true, 
      "bounds": [
        [
          46, 
          706
        ], 
        [
          1394, 
          827
        ]
      ], 
      "signature": "[class]android.widget.RelativeLayout[resource_id]com.yelp.android:id/term_description[text]None[enabled,,]"
    }, 
    {
      "content_description": null, 
      "resource_id": "com.yelp.android:id/term", 
      "text": "Hair Salons for Women", 
      "visible": true, 
      "checkable": false, 
      "children": [], 
      "size": "648*85", 
      "checked": false, 
      "temp_id": 24, 
      "selected": false, 
      "child_count": 0, 
      "content_free_signature": "[class]android.widget.TextView[resource_id]com.yelp.android:id/term", 
      "is_password": false, 
      "parent": 23, 
      "focusable": false, 
      "editable": false, 
      "focused": false, 
      "clickable": false, 
      "class": "android.widget.TextView", 
      "scrollable": false, 
      "package": "com.yelp.android", 
      "long_clickable": false, 
      "view_str": "e2ec8d85c53203ac50386a6ff7f498ed", 
      "enabled": true, 
      "bounds": [
        [
          46, 
          724
        ], 
        [
          694, 
          809
        ]
      ], 
      "signature": "[class]android.widget.TextView[resource_id]com.yelp.android:id/term[text]Hair Salons for Women[enabled,,]"
    }, 
    {
      "content_description": null, 
      "resource_id": "com.yelp.android:id/description", 
      "text": null, 
      "visible": true, 
      "checkable": false, 
      "children": [], 
      "size": "36*121", 
      "checked": false, 
      "temp_id": 25, 
      "selected": false, 
      "child_count": 0, 
      "content_free_signature": "[class]android.widget.TextView[resource_id]com.yelp.android:id/description", 
      "is_password": false, 
      "parent": 23, 
      "focusable": false, 
      "editable": false, 
      "focused": false, 
      "clickable": false, 
      "class": "android.widget.TextView", 
      "scrollable": false, 
      "package": "com.yelp.android", 
      "long_clickable": false, 
      "view_str": "a087ed2f85a36ca33676fb902785bc33", 
      "enabled": true, 
      "bounds": [
        [
          694, 
          706
        ], 
        [
          730, 
          827
        ]
      ], 
      "signature": "[class]android.widget.TextView[resource_id]com.yelp.android:id/description[text]None[enabled,,]"
    }, 
    {
      "content_description": null, 
      "resource_id": null, 
      "text": null, 
      "visible": true, 
      "checkable": false, 
      "children": [
        27
      ], 
      "size": "1440*191", 
      "checked": false, 
      "temp_id": 26, 
      "selected": false, 
      "child_count": 1, 
      "content_free_signature": "[class]android.widget.RelativeLayout[resource_id]None", 
      "is_password": false, 
      "parent": 17, 
      "focusable": false, 
      "editable": false, 
      "focused": false, 
      "clickable": true, 
      "class": "android.widget.RelativeLayout", 
      "scrollable": false, 
      "package": "com.yelp.android", 
      "long_clickable": false, 
      "view_str": "347f4e721d4ad4625577fb41f924bbec", 
      "enabled": true, 
      "bounds": [
        [
          0, 
          862
        ], 
        [
          1440, 
          1053
        ]
      ], 
      "signature": "[class]android.widget.RelativeLayout[resource_id]None[text]None[enabled,,]"
    }, 
    {
      "content_description": null, 
      "resource_id": "com.yelp.android:id/term_description", 
      "text": null, 
      "visible": true, 
      "checkable": false, 
      "children": [
        28, 
        29
      ], 
      "size": "1348*121", 
      "checked": false, 
      "temp_id": 27, 
      "selected": false, 
      "child_count": 2, 
      "content_free_signature": "[class]android.widget.RelativeLayout[resource_id]com.yelp.android:id/term_description", 
      "is_password": false, 
      "parent": 26, 
      "focusable": false, 
      "editable": false, 
      "focused": false, 
      "clickable": false, 
      "class": "android.widget.RelativeLayout", 
      "scrollable": false, 
      "package": "com.yelp.android", 
      "long_clickable": false, 
      "view_str": "3fac789f34c4f67fd6ff8072a075bf49", 
      "enabled": true, 
      "bounds": [
        [
          46, 
          897
        ], 
        [
          1394, 
          1018
        ]
      ], 
      "signature": "[class]android.widget.RelativeLayout[resource_id]com.yelp.android:id/term_description[text]None[enabled,,]"
    }, 
    {
      "content_description": null, 
      "resource_id": "com.yelp.android:id/term", 
      "text": "Men's Hair Salons", 
      "visible": true, 
      "checkable": false, 
      "children": [], 
      "size": "497*85", 
      "checked": false, 
      "temp_id": 28, 
      "selected": false, 
      "child_count": 0, 
      "content_free_signature": "[class]android.widget.TextView[resource_id]com.yelp.android:id/term", 
      "is_password": false, 
      "parent": 27, 
      "focusable": false, 
      "editable": false, 
      "focused": false, 
      "clickable": false, 
      "class": "android.widget.TextView", 
      "scrollable": false, 
      "package": "com.yelp.android", 
      "long_clickable": false, 
      "view_str": "d9627ec387f2eb15d24efff0fdd32b16", 
      "enabled": true, 
      "bounds": [
        [
          46, 
          915
        ], 
        [
          543, 
          1000
        ]
      ], 
      "signature": "[class]android.widget.TextView[resource_id]com.yelp.android:id/term[text]Men's Hair Salons[enabled,,]"
    }, 
    {
      "content_description": null, 
      "resource_id": "com.yelp.android:id/description", 
      "text": null, 
      "visible": true, 
      "checkable": false, 
      "children": [], 
      "size": "36*121", 
      "checked": false, 
      "temp_id": 29, 
      "selected": false, 
      "child_count": 0, 
      "content_free_signature": "[class]android.widget.TextView[resource_id]com.yelp.android:id/description", 
      "is_password": false, 
      "parent": 27, 
      "focusable": false, 
      "editable": false, 
      "focused": false, 
      "clickable": false, 
      "class": "android.widget.TextView", 
      "scrollable": false, 
      "package": "com.yelp.android", 
      "long_clickable": false, 
      "view_str": "a087ed2f85a36ca33676fb902785bc33", 
      "enabled": true, 
      "bounds": [
        [
          543, 
          897
        ], 
        [
          579, 
          1018
        ]
      ], 
      "signature": "[class]android.widget.TextView[resource_id]com.yelp.android:id/description[text]None[enabled,,]"
    }, 
    {
      "content_description": null, 
      "resource_id": null, 
      "text": null, 
      "visible": true, 
      "checkable": false, 
      "children": [
        31
      ], 
      "size": "1440*191", 
      "checked": false, 
      "temp_id": 30, 
      "selected": false, 
      "child_count": 1, 
      "content_free_signature": "[class]android.widget.RelativeLayout[resource_id]None", 
      "is_password": false, 
      "parent": 17, 
      "focusable": false, 
      "editable": false, 
      "focused": false, 
      "clickable": true, 
      "class": "android.widget.RelativeLayout", 
      "scrollable": false, 
      "package": "com.yelp.android", 
      "long_clickable": false, 
      "view_str": "347f4e721d4ad4625577fb41f924bbec", 
      "enabled": true, 
      "bounds": [
        [
          0, 
          1053
        ], 
        [
          1440, 
          1244
        ]
      ], 
      "signature": "[class]android.widget.RelativeLayout[resource_id]None[text]None[enabled,,]"
    }, 
    {
      "content_description": null, 
      "resource_id": "com.yelp.android:id/term_description", 
      "text": null, 
      "visible": true, 
      "checkable": false, 
      "children": [
        32, 
        33
      ], 
      "size": "1348*121", 
      "checked": false, 
      "temp_id": 31, 
      "selected": false, 
      "child_count": 2, 
      "content_free_signature": "[class]android.widget.RelativeLayout[resource_id]com.yelp.android:id/term_description", 
      "is_password": false, 
      "parent": 30, 
      "focusable": false, 
      "editable": false, 
      "focused": false, 
      "clickable": false, 
      "class": "android.widget.RelativeLayout", 
      "scrollable": false, 
      "package": "com.yelp.android", 
      "long_clickable": false, 
      "view_str": "9ec03bfdc5a1c717ca3528f282fec422", 
      "enabled": true, 
      "bounds": [
        [
          46, 
          1088
        ], 
        [
          1394, 
          1209
        ]
      ], 
      "signature": "[class]android.widget.RelativeLayout[resource_id]com.yelp.android:id/term_description[text]None[enabled,,]"
    }, 
    {
      "content_description": null, 
      "resource_id": "com.yelp.android:id/term", 
      "text": "African American Hair Salons", 
      "visible": true, 
      "checkable": false, 
      "children": [], 
      "size": "831*85", 
      "checked": false, 
      "temp_id": 32, 
      "selected": false, 
      "child_count": 0, 
      "content_free_signature": "[class]android.widget.TextView[resource_id]com.yelp.android:id/term", 
      "is_password": false, 
      "parent": 31, 
      "focusable": false, 
      "editable": false, 
      "focused": false, 
      "clickable": false, 
      "class": "android.widget.TextView", 
      "scrollable": false, 
      "package": "com.yelp.android", 
      "long_clickable": false, 
      "view_str": "614a0b77a9328fa11f4b990d651c2e5b", 
      "enabled": true, 
      "bounds": [
        [
          46, 
          1106
        ], 
        [
          877, 
          1191
        ]
      ], 
      "signature": "[class]android.widget.TextView[resource_id]com.yelp.android:id/term[text]African American Hair Salons[enabled,,]"
    }, 
    {
      "content_description": null, 
      "resource_id": "com.yelp.android:id/description", 
      "text": null, 
      "visible": true, 
      "checkable": false, 
      "children": [], 
      "size": "36*121", 
      "checked": false, 
      "temp_id": 33, 
      "selected": false, 
      "child_count": 0, 
      "content_free_signature": "[class]android.widget.TextView[resource_id]com.yelp.android:id/description", 
      "is_password": false, 
      "parent": 31, 
      "focusable": false, 
      "editable": false, 
      "focused": false, 
      "clickable": false, 
      "class": "android.widget.TextView", 
      "scrollable": false, 
      "package": "com.yelp.android", 
      "long_clickable": false, 
      "view_str": "a087ed2f85a36ca33676fb902785bc33", 
      "enabled": true, 
      "bounds": [
        [
          877, 
          1088
        ], 
        [
          913, 
          1209
        ]
      ], 
      "signature": "[class]android.widget.TextView[resource_id]com.yelp.android:id/description[text]None[enabled,,]"
    }, 
    {
      "content_description": null, 
      "resource_id": null, 
      "text": null, 
      "visible": true, 
      "checkable": false, 
      "children": [
        35
      ], 
      "size": "1440*191", 
      "checked": false, 
      "temp_id": 34, 
      "selected": false, 
      "child_count": 1, 
      "content_free_signature": "[class]android.widget.RelativeLayout[resource_id]None", 
      "is_password": false, 
      "parent": 17, 
      "focusable": false, 
      "editable": false, 
      "focused": false, 
      "clickable": true, 
      "class": "android.widget.RelativeLayout", 
      "scrollable": false, 
      "package": "com.yelp.android", 
      "long_clickable": false, 
      "view_str": "347f4e721d4ad4625577fb41f924bbec", 
      "enabled": true, 
      "bounds": [
        [
          0, 
          1244
        ], 
        [
          1440, 
          1435
        ]
      ], 
      "signature": "[class]android.widget.RelativeLayout[resource_id]None[text]None[enabled,,]"
    }, 
    {
      "content_description": null, 
      "resource_id": "com.yelp.android:id/term_description", 
      "text": null, 
      "visible": true, 
      "checkable": false, 
      "children": [
        36, 
        37
      ], 
      "size": "1348*121", 
      "checked": false, 
      "temp_id": 35, 
      "selected": false, 
      "child_count": 2, 
      "content_free_signature": "[class]android.widget.RelativeLayout[resource_id]com.yelp.android:id/term_description", 
      "is_password": false, 
      "parent": 34, 
      "focusable": false, 
      "editable": false, 
      "focused": false, 
      "clickable": false, 
      "class": "android.widget.RelativeLayout", 
      "scrollable": false, 
      "package": "com.yelp.android", 
      "long_clickable": false, 
      "view_str": "0b0e121cabf8ec26b0c6484e7cc630f0", 
      "enabled": true, 
      "bounds": [
        [
          46, 
          1279
        ], 
        [
          1394, 
          1400
        ]
      ], 
      "signature": "[class]android.widget.RelativeLayout[resource_id]com.yelp.android:id/term_description[text]None[enabled,,]"
    }, 
    {
      "content_description": null, 
      "resource_id": "com.yelp.android:id/term", 
      "text": "Dominican Hair Salons", 
      "visible": true, 
      "checkable": false, 
      "children": [], 
      "size": "639*85", 
      "checked": false, 
      "temp_id": 36, 
      "selected": false, 
      "child_count": 0, 
      "content_free_signature": "[class]android.widget.TextView[resource_id]com.yelp.android:id/term", 
      "is_password": false, 
      "parent": 35, 
      "focusable": false, 
      "editable": false, 
      "focused": false, 
      "clickable": false, 
      "class": "android.widget.TextView", 
      "scrollable": false, 
      "package": "com.yelp.android", 
      "long_clickable": false, 
      "view_str": "6eb3ce213e8d63357800776df52e47b1", 
      "enabled": true, 
      "bounds": [
        [
          46, 
          1297
        ], 
        [
          685, 
          1382
        ]
      ], 
      "signature": "[class]android.widget.TextView[resource_id]com.yelp.android:id/term[text]Dominican Hair Salons[enabled,,]"
    }, 
    {
      "content_description": null, 
      "resource_id": "com.yelp.android:id/description", 
      "text": null, 
      "visible": true, 
      "checkable": false, 
      "children": [], 
      "size": "36*121", 
      "checked": false, 
      "temp_id": 37, 
      "selected": false, 
      "child_count": 0, 
      "content_free_signature": "[class]android.widget.TextView[resource_id]com.yelp.android:id/description", 
      "is_password": false, 
      "parent": 35, 
      "focusable": false, 
      "editable": false, 
      "focused": false, 
      "clickable": false, 
      "class": "android.widget.TextView", 
      "scrollable": false, 
      "package": "com.yelp.android", 
      "long_clickable": false, 
      "view_str": "a087ed2f85a36ca33676fb902785bc33", 
      "enabled": true, 
      "bounds": [
        [
          685, 
          1279
        ], 
        [
          721, 
          1400
        ]
      ], 
      "signature": "[class]android.widget.TextView[resource_id]com.yelp.android:id/description[text]None[enabled,,]"
    }, 
    {
      "content_description": null, 
      "resource_id": null, 
      "text": null, 
      "visible": true, 
      "checkable": false, 
      "children": [
        39
      ], 
      "size": "1440*191", 
      "checked": false, 
      "temp_id": 38, 
      "selected": false, 
      "child_count": 1, 
      "content_free_signature": "[class]android.widget.RelativeLayout[resource_id]None", 
      "is_password": false, 
      "parent": 17, 
      "focusable": false, 
      "editable": false, 
      "focused": false, 
      "clickable": true, 
      "class": "android.widget.RelativeLayout", 
      "scrollable": false, 
      "package": "com.yelp.android", 
      "long_clickable": false, 
      "view_str": "347f4e721d4ad4625577fb41f924bbec", 
      "enabled": true, 
      "bounds": [
        [
          0, 
          1435
        ], 
        [
          1440, 
          1626
        ]
      ], 
      "signature": "[class]android.widget.RelativeLayout[resource_id]None[text]None[enabled,,]"
    }, 
    {
      "content_description": null, 
      "resource_id": "com.yelp.android:id/term_description", 
      "text": null, 
      "visible": true, 
      "checkable": false, 
      "children": [
        40, 
        41
      ], 
      "size": "1348*121", 
      "checked": false, 
      "temp_id": 39, 
      "selected": false, 
      "child_count": 2, 
      "content_free_signature": "[class]android.widget.RelativeLayout[resource_id]com.yelp.android:id/term_description", 
      "is_password": false, 
      "parent": 38, 
      "focusable": false, 
      "editable": false, 
      "focused": false, 
      "clickable": false, 
      "class": "android.widget.RelativeLayout", 
      "scrollable": false, 
      "package": "com.yelp.android", 
      "long_clickable": false, 
      "view_str": "948b9e754537de87b3ed518edf47af60", 
      "enabled": true, 
      "bounds": [
        [
          46, 
          1470
        ], 
        [
          1394, 
          1591
        ]
      ], 
      "signature": "[class]android.widget.RelativeLayout[resource_id]com.yelp.android:id/term_description[text]None[enabled,,]"
    }, 
    {
      "content_description": null, 
      "resource_id": "com.yelp.android:id/term", 
      "text": "Hair Stylists", 
      "visible": true, 
      "checkable": false, 
      "children": [], 
      "size": "346*85", 
      "checked": false, 
      "temp_id": 40, 
      "selected": false, 
      "child_count": 0, 
      "content_free_signature": "[class]android.widget.TextView[resource_id]com.yelp.android:id/term", 
      "is_password": false, 
      "parent": 39, 
      "focusable": false, 
      "editable": false, 
      "focused": false, 
      "clickable": false, 
      "class": "android.widget.TextView", 
      "scrollable": false, 
      "package": "com.yelp.android", 
      "long_clickable": false, 
      "view_str": "1401561ed175d9237eb6966cf0304d5e", 
      "enabled": true, 
      "bounds": [
        [
          46, 
          1488
        ], 
        [
          392, 
          1573
        ]
      ], 
      "signature": "[class]android.widget.TextView[resource_id]com.yelp.android:id/term[text]Hair Stylists[enabled,,]"
    }, 
    {
      "content_description": null, 
      "resource_id": "com.yelp.android:id/description", 
      "text": null, 
      "visible": true, 
      "checkable": false, 
      "children": [], 
      "size": "36*121", 
      "checked": false, 
      "temp_id": 41, 
      "selected": false, 
      "child_count": 0, 
      "content_free_signature": "[class]android.widget.TextView[resource_id]com.yelp.android:id/description", 
      "is_password": false, 
      "parent": 39, 
      "focusable": false, 
      "editable": false, 
      "focused": false, 
      "clickable": false, 
      "class": "android.widget.TextView", 
      "scrollable": false, 
      "package": "com.yelp.android", 
      "long_clickable": false, 
      "view_str": "a087ed2f85a36ca33676fb902785bc33", 
      "enabled": true, 
      "bounds": [
        [
          392, 
          1470
        ], 
        [
          428, 
          1591
        ]
      ], 
      "signature": "[class]android.widget.TextView[resource_id]com.yelp.android:id/description[text]None[enabled,,]"
    }, 
    {
      "content_description": null, 
      "resource_id": "com.yelp.android:id/tint", 
      "text": null, 
      "visible": true, 
      "checkable": false, 
      "children": [], 
      "size": "1440*766", 
      "checked": false, 
      "temp_id": 42, 
      "selected": false, 
      "child_count": 0, 
      "content_free_signature": "[class]android.view.View[resource_id]com.yelp.android:id/tint", 
      "is_password": false, 
      "parent": 8, 
      "focusable": false, 
      "editable": false, 
      "focused": false, 
      "clickable": true, 
      "class": "android.view.View", 
      "scrollable": false, 
      "package": "com.yelp.android", 
      "long_clickable": false, 
      "view_str": "6d6af54552aa2b5178f25704264ae22b", 
      "enabled": true, 
      "bounds": [
        [
          0, 
          1626
        ], 
        [
          1440, 
          2392
        ]
      ], 
      "signature": "[class]android.view.View[resource_id]com.yelp.android:id/tint[text]None[enabled,,]"
    }, 
    {
      "content_description": null, 
      "resource_id": "android:id/statusBarBackground", 
      "text": null, 
      "visible": false, 
      "checkable": false, 
      "children": [], 
      "size": "1440*84", 
      "checked": false, 
      "temp_id": 43, 
      "selected": false, 
      "child_count": 0, 
      "content_free_signature": "[class]android.view.View[resource_id]android:id/statusBarBackground", 
      "is_password": false, 
      "parent": 0, 
      "focusable": false, 
      "editable": false, 
      "focused": false, 
      "clickable": false, 
      "class": "android.view.View", 
      "scrollable": false, 
      "package": "com.yelp.android", 
      "long_clickable": false, 
      "view_str": "14434e0f6c4ba279e814b2ea6cf746fe", 
      "enabled": true, 
      "bounds": [
        [
          0, 
          0
        ], 
        [
          1440, 
          84
        ]
      ], 
      "signature": "[class]android.view.View[resource_id]android:id/statusBarBackground[text]None[enabled,,]"
    }, 
    {
      "content_description": null, 
      "resource_id": "android:id/navigationBarBackground", 
      "text": null, 
      "visible": false, 
      "checkable": false, 
      "children": [], 
      "size": "1440*168", 
      "checked": false, 
      "temp_id": 44, 
      "selected": false, 
      "child_count": 0, 
      "content_free_signature": "[class]android.view.View[resource_id]android:id/navigationBarBackground", 
      "is_password": false, 
      "parent": 0, 
      "focusable": false, 
      "editable": false, 
      "focused": false, 
      "clickable": false, 
      "class": "android.view.View", 
      "scrollable": false, 
      "package": "com.yelp.android", 
      "long_clickable": false, 
      "view_str": "32a79e87b59caae91175ab2c15d3f6c1", 
      "enabled": true, 
      "bounds": [
        [
          0, 
          2392
        ], 
        [
          1440, 
          2560
        ]
      ], 
      "signature": "[class]android.view.View[resource_id]android:id/navigationBarBackground[text]None[enabled,,]"
    }
  ], 
  "state_str_content_free": "c3015b69d20b90152c5b8ca385dd8028", 
  "activity_stack": [
    "com.yelp.android/.ui.activities.search.SearchOverlay", 
    "com.yelp.android/.ui.activities.search.SearchBusinessesByList", 
    "com.yelp.android/.ui.activities.profile.ActivityUserProfile", 
    "com.yelp.android/.ui.activities.profile.ActivityUserProfile", 
    "com.yelp.android/.ui.activities.search.SearchBusinessesByList", 
    "com.yelp.android/.ui.activities.feed.ActivityFeed", 
    "com.yelp.android/.ui.activities.profile.ActivityUserProfile", 
    "com.yelp.android/.ui.activities.feed.ActivityFeed", 
    "com.yelp.android/.ui.activities.search.SearchBusinessesByList", 
    "com.yelp.android/.ui.activities.bookmarks.ActivityBookmarks", 
    "com.yelp.android/.ui.activities.profile.ActivityUserProfile", 
    "com.yelp.android/.ui.activities.bookmarks.ActivityBookmarks", 
    "com.yelp.android/.ui.activities.feed.ActivityFeed", 
    "com.yelp.android/.ui.activities.bookmarks.ActivityBookmarks", 
    "com.yelp.android/.ui.activities.search.SearchBusinessesByList", 
    "com.yelp.android/.ui.activities.nearby.ActivityNearby"
  ], 
  "background_services": [
    "com.android.bluetooth/.hid.HidService", 
    "com.snapchat.android/.service.SnapchatService", 
    "com.google.android.apps.messaging/com.google.android.ims.service.JibeService", 
    "com.huawei.callstatisticsutils/.CallStatisticsService", 
    "com.facebook.katana/com.facebook.video.vps.VideoPlayerService", 
    "org.codeaurora.ims/.ImsService", 
    "io.github.privacystreams.app/.db.PStreamCollectService", 
    "com.google.android.gms/.deviceconnection.service.DeviceConnectionWatcherService", 
    "com.google.android.gms/com.google.android.location.places.service.PlaceDetectionAsyncService", 
    "com.google.android.gms/.tapandpay.hce.service.TpHceService", 
    "com.android.systemui/.keyguard.KeyguardService", 
    "com.android.bluetooth/.btservice.AdapterService", 
    "com.google.android.gms/.instantapps.service.InstantAppsService", 
    "com.android.systemui/.ImageWallpaper", 
    "com.google.android.inputmethod.latin/com.android.inputmethod.latin.spellcheck.AndroidSpellCheckerService", 
    "com.google.android.gms/com.google.android.location.geocode.GeocodeService", 
    "io.github.privacystreams.app/io.github.privacystreams.notification.PSNotificationListenerService", 
    "com.google.android.gms/.auth.setup.devicesignals.LockScreenService", 
    "com.google.android.gms/.gcm.GcmService", 
    "com.google.android.gms/.analytics.service.AnalyticsService", 
    "com.google.android.gms/com.google.location.nearby.direct.service.NearbyDirectService", 
    "com.google.android.gms/.chimera.PersistentBoundBrokerService", 
    "com.android.bluetooth/.gatt.GattService", 
    "net.loadinghome.smartunlock/.Servicio", 
    "com.google.android.gms/.auth.account.service.WorkAccountService", 
    "com.google.android.gms/com.google.android.location.fused.service.FusedProviderService", 
    "com.google.android.gms/.pseudonymous.service.PseudonymousIdService", 
    "com.instagram.android/com.facebook.rti.push.service.FbnsService", 
    "com.android.vending/com.google.android.finsky.contentfilter.impl.ContentFiltersService", 
    "io.github.ylimit.droidbotapp/.DroidBotIME", 
    "com.android.bluetooth/.pbap.BluetoothPbapService", 
    "com.google.android.gms/.beacon.BleService", 
    "com.google.android.gms/.update.SystemUpdateService", 
    "com.google.android.gms/com.google.android.location.fused.FusedLocationService", 
    "com.android.bluetooth/.a2dp.A2dpService", 
    "com.qualcomm.qcrilmsgtunnel/.QcrilMsgTunnelService", 
    "com.qualcomm.cabl/.CABLService", 
    "io.github.ylimit.droidbotapp/io.github.privacystreams.accessibility.PSAccessibilityService", 
    "com.google.android.gms/com.google.android.location.geofencer.service.GeofenceProviderService", 
    "com.android.systemui/.SystemUIService", 
    "android/.hardware.location.GeofenceHardwareService", 
    "com.google.android.gms/com.google.android.location.reporting.service.DispatchingService", 
    "com.facebook.katana/com.facebook.rti.orca.MainService", 
    "com.huawei.sarcontrolservice/.SarControlService", 
    "com.google.android.gms/com.google.android.location.internal.PendingIntentCallbackService", 
    "com.tms.easyro.nopspro/com.tms.pdf.util.NopsService", 
    "com.google.android.gms/.nearby.messages.service.NearbyMessagesService", 
    "com.android.server.telecom/.components.BluetoothPhoneService", 
    "com.google.android.googlequicksearchbox/com.google.android.apps.gsa.search.core.service.SearchService", 
    "english.grammar.test.app/io.presage.PresageService", 
    "com.google.android.gms/com.google.android.location.internal.server.GoogleLocationService", 
    "com.google.android.gms/com.google.android.contextmanager.service.ContextManagerService", 
    "com.google.android.gms/com.google.android.location.network.NetworkLocationService", 
    "com.android.stk/.StkAppService", 
    "com.facebook.katana/com.facebook.rti.push.service.FbnsService", 
    "com.google.android.gms/com.google.android.location.internal.GoogleLocationManagerService", 
    "me.twrp.twrpapp/me.twrp.officialtwrpapp.OnBootService", 
    "com.android.server.telecom/.components.TelecomService", 
    "com.android.providers.media/.MtpService", 
    "com.android.bluetooth/.hfp.HeadsetService", 
    "com.google.android.googlequicksearchbox/com.google.android.voiceinteraction.GsaVoiceInteractionService", 
    "android/com.android.internal.backup.LocalTransportService", 
    "com.google.android.gms/.lockbox.service.LockboxBrokerService", 
    "com.google.android.gms/.common.stats.GmsCoreStatsService", 
    "com.google.android.gms/.clearcut.service.ClearcutLoggerService", 
    "com.google.android.gms/com.google.android.location.internal.server.HardwareArProviderService", 
    "com.android.bluetooth/.map.BluetoothMapService", 
    "com.android.mms.service/.MmsService", 
    "com.android.phone/.TelephonyDebugService", 
    "com.google.android.gms/.udc.service.UdcApiService", 
    "com.google.android.gms/.icing.service.IndexService", 
    "com.android.bluetooth/.pan.PanService", 
    "com.google.android.gms/.backup.BackupTransportService"
  ], 
  "state_str": "69bedf7eafa58edbee51b4b989e5b234", 
  "tag": "2017-08-11_202521", 
  "foreground_activity": "com.yelp.android/.ui.activities.search.SearchOverlay"
}